motion_detector_g4/__init__.py
motion_detector_g4-1.2.0.dist-info/LICENSE
motion_detector_g4-1.2.0.dist-info/METADATA
motion_detector_g4-1.2.0.dist-info/WHEEL
motion_detector_g4-1.2.0.dist-info/top_level.txt
motion_detector_g4-1.2.0.dist-info/RECORD
