Metadata-Version: 2.1
Name: motion-detector-g4
Version: 1.2.0
Summary: Motion Detector
Home-page: https://github.com/Genzo4/motion_detector
Author: Genzo
Author-email: genzo@bk.ru
License: MIT
Project-URL: Bug Tracker, https://github.com/Genzo4/motion_detector/issues
Keywords: motiondetector,motion_detector,motion-detector,opencv,opencv-contrib-python,g4
Classifier: Development Status :: 5 - Production/Stable
Classifier: Programming Language :: Python :: 3
Classifier: Programming Language :: Python :: 3.6
Classifier: Programming Language :: Python :: 3.7
Classifier: Programming Language :: Python :: 3.8
Classifier: Programming Language :: Python :: 3.9
Classifier: Programming Language :: Python :: 3.10
Classifier: Programming Language :: Python :: 3.11
Classifier: License :: OSI Approved :: MIT License
Classifier: Operating System :: OS Independent
Classifier: Intended Audience :: Developers
Classifier: Intended Audience :: Education
Classifier: Intended Audience :: Information Technology
Classifier: Natural Language :: English
Classifier: Natural Language :: Russian
Classifier: Topic :: Scientific/Engineering
Classifier: Topic :: Scientific/Engineering :: Image Recognition
Classifier: Topic :: Software Development
Classifier: Topic :: Software Development :: Libraries :: Python Modules
Requires-Python: >=3.6
License-File: LICENSE
Requires-Dist: opencv-contrib-python ==4.5.5.64
Requires-Dist: numpy
Requires-Dist: utilspy-g4 >=2.2.0
